costa_utils/__init__.py
costa_utils/hf_viz.py
costa_utils-0.1.1.dist-info/LICENSE
costa_utils-0.1.1.dist-info/METADATA
costa_utils-0.1.1.dist-info/WHEEL
costa_utils-0.1.1.dist-info/RECORD
